Workbook
Name Slicer_Region: #N/A
Name Slicer_Years: #N/A

Sheet Sheet4
A3: Qtr1 | B3: Sum of 648.0736987
A4: Qtr1 | B4: 348.13157
A5: Qtr2 | B5: 1288.9413
A6: Qtr3 | B6: 1336.0176
A7: Qtr4 | B7: 972.63428

Sheet Sheet5
A3: Qtr1 | B3: Sum of 648.0736987
A4: Qtr1 | B4: 348.13157
A5: Qtr2 | B5: 1288.9413
A6: Qtr3 | B6: 1336.0176
A7: Qtr4 | B7: 972.63428

Sheet Sheet1
A3: Sum of Total Sales | B3: Sum of Units Sold | C3: Average of Price per Unit | D3: Sum of Operating Profit
A4: 12016665 | B4: 24788610 | C4: 0.45216625 | D4: 4722496.8
A7: Sum of Total Sales2 | B7: Column Labels
A8: Row Labels | B8: 2022 | C8: 2023 | D8: Grand Total
A9: Coca-Cola | B9: 499102 | C9: 2268974.9 | D9: 2768076.9
A10: Dasani Water | B10: 469270.7 | C10: 1917827.8 | D10: 2387098.5
A11: Diet Coke | B11: 423758.7 | C11: 1633959.3 | D11: 2057718
A12: Fanta | B12: 315489.2 | C12: 1116062.9 | D12: 1431552.1
A13: Powerade | B13: 349533.9 | C13: 1302529.3 | D13: 1652063.2
A14: Sprite | B14: 366578 | C14: 1353578.3 | D14: 1720156.3
A15: Grand Total | B15: 2423732.5 | C15: 9592932.5 | D15: 12016665
A18: Sum of Total Sales2 | B18: Column Labels
A19: Row Labels | B19: 2022 | C19: 2023 | D19: Grand Total
A20: Amazon | B20: 276210 | C20: 1009698.7 | D20: 1285908.7
A21: BevCo | B21: 466788 | C21: 2327606.5 | D21: 2794394.5
A22: FizzyCo | B22: 161210.1 | C22: 2262827.1 | D22: 2424037.2
A23: Target | B23: 9250.3 | C23: 1341995 | D23: 1351245.3
A24: Walmart | B24: 339912.5 | C24: 580211 | D24: 920123.5
A25: West Soda | B25: 1170361.6 | C25: 2070594.2 | D25: 3240955.8
A26: Grand Total | B26: 2423732.5 | C26: 9592932.5 | D26: 12016665
A28: Years | B28: Quarters | C28: Sum of Operating Profit
A29: 2022 | B29: Qtr1 | C29: 255989.11 | E29: =A29 -> 2022 | F29: =B29 -> Qtr1 | G29: =C29 -> 255989.11
B30: Qtr2 | C30: 238312.39 | F30: =B30 -> Qtr2 | G30: =C30 -> 238312.39
B31: Qtr3 | C31: 270003.46 | F31: =B31 -> Qtr3 | G31: =C31 -> 270003.46
B32: Qtr4 | C32: 137245.54 | F32: =B32 -> Qtr4 | G32: =C32 -> 137245.54
A33: 2023 | B33: Qtr1 | C33: 711580.94 | E33: =A33 -> 2023 | F33: =B33 -> Qtr1 | G33: =C33 -> 711580.94
B34: Qtr2 | C34: 953054.46 | F34: =B34 -> Qtr2 | G34: =C34 -> 953054.46
B35: Qtr3 | C35: 1139523.7 | F35: =B35 -> Qtr3 | G35: =C35 -> 1139523.7
B36: Qtr4 | C36: 1016787.1 | F36: =B36 -> Qtr4 | G36: =C36 -> 1016787.1
A37: Grand Total | C37: 4722496.8

Sheet Sheet3
A3: Sum of Total Sales | B3: Sum of Units Sold | C3: Average of Price per Unit | D3: Sum of Operating Profit
A4: 12016665 | B4: 24788610 | C4: 0.45216625 | D4: 4722496.8
A7: Sum of Total Sales | B7: Column Labels
A8: Row Labels | B8: 2022 | C8: 2023 | D8: Total
A9: Coca-Cola | B9: 84857 | C9: 384526.6 | D9: 469383.6 | F9: =B8 -> 2022 | G9: =C8 -> 2023 | H9: =D8 -> Total
A10: Dasani Water | B10: 76834 | C10: 334144.6 | D10: 410978.6 | F10: =B9 -> 84857 | G10: =C9 -> 384526.6 | H10: =D9 -> 469383.6
A11: Diet Coke | B11: 59939 | C11: 305425.5 | D11: 365364.5 | F11: =B10 -> 76834 | G11: =C10 -> 334144.6 | H11: =D10 -> 410978.6
A12: Fanta | B12: 48147.7 | C12: 219257.1 | D12: 267404.8 | F12: =B11 -> 59939 | G12: =C11 -> 305425.5 | H12: =D11 -> 365364.5
A13: Powerade | B13: 66209.2 | C13: 252114.5 | D13: 318323.7 | F13: =B12 -> 48147.7 | G13: =C12 -> 219257.1 | H13: =D12 -> 267404.8
A14: Sprite | B14: 51424.4 | C14: 254564 | D14: 305988.4 | F14: =B13 -> 66209.2 | G14: =C13 -> 252114.5 | H14: =D13 -> 318323.7
A15: Total | B15: 387411.3 | C15: 1750032.3 | D15: 2137443.6 | F15: =B14 -> 51424.4 | G15: =C14 -> 254564 | H15: =D14 -> 305988.4
A18: Sum of Total Sales | B18: Column Labels
A19: Row Labels | B19: 2022 | C19: 2023 | D19: Total
A20: Amazon | C20: 133200.8 | D20: 133200.8
A21: BevCo | B21: 117386.1 | C21: 659450.7 | D21: 776836.8
A22: FizzyCo | B22: 114876 | C22: 589183.3 | D22: 704059.3
A23: Walmart | C23: 299203.9 | D23: 299203.9
A24: West Soda | B24: 155149.2 | C24: 68993.6 | D24: 224142.8
A25: Total | B25: 387411.3 | C25: 1750032.3 | D25: 2137443.6
A29: Row Labels | B29: Sum of Operating Profit
A30: 2022
A31: Qtr2 | B31: 46582.663
A32: Qtr3 | B32: 87249.726
A33: Qtr4 | B33: 24106.397
A34: 2023 | B34: 681367.13
A35: Grand Total | B35: 839305.92

Sheet Data
B2: Retailer Dataset
B4: Retailer | C4: Retailer ID | D4: Invoice Date | E4: Region | F4: State | G4: City | H4: Beverage Brand | I4: Price per Unit | J4: Units Sold | K4: Total Sales | L4: Operating Profit | M4: Operating Margin
B5: BevCo | C5: 1185732 | D5: 44562 | E5: Northeast | F5: New York | G5: New York | H5: Coca-Cola | I5: 0.5 | J5: 12000 | K5: 6000 | L5: 3000 | M5: 0.5
B6: BevCo | C6: 1185732 | D6: 44563 | E6: Northeast | F6: New York | G6: New York | H6: Diet Coke | I6: 0.5 | J6: 10000 | K6: 5000 | L6: 1500 | M6: 0.3
B7: BevCo | C7: 1185732 | D7: 44564 | E7: Northeast | F7: New York | G7: New York | H7: Sprite | I7: 0.4 | J7: 10000 | K7: 4000 | L7: 1400 | M7: 0.35
B8: BevCo | C8: 1185732 | D8: 44565 | E8: Northeast | F8: New York | G8: New York | H8: Fanta | I8: 0.45 | J8: 8500 | K8: 3825 | L8: 1338.75 | M8: 0.35
B9: BevCo | C9: 1185732 | D9: 44566 | E9: Northeast | F9: New York | G9: New York | H9: Powerade | I9: 0.6 | J9: 9000 | K9: 5400 | L9: 1620 | M9: 0.3
B10: BevCo | C10: 1185732 | D10: 44567 | E10: Northeast | F10: New York | G10: New York | H10: Dasani Water | I10: 0.5 | J10: 10000 | K10: 5000 | L10: 1250 | M10: 0.25
B11: BevCo | C11: 1185732 | D11: 44568 | E11: Northeast | F11: New York | G11: New York | H11: Coca-Cola | I11: 0.5 | J11: 12500 | K11: 6250 | L11: 3125 | M11: 0.5
B12: BevCo | C12: 1185732 | D12: 44569 | E12: Northeast | F12: New York | G12: New York | H12: Diet Coke | I12: 0.5 | J12: 9000 | K12: 4500 | L12: 1350 | M12: 0.3
B13: BevCo | C13: 1185732 | D13: 44582 | E13: Northeast | F13: New York | G13: New York | H13: Sprite | I13: 0.4 | J13: 9500 | K13: 3800 | L13: 1330 | M13: 0.35
B14: BevCo | C14: 1185732 | D14: 44583 | E14: Northeast | F14: New York | G14: New York | H14: Fanta | I14: 0.45 | J14: 8250 | K14: 3712.5 | L14: 1299.375 | M14: 0.35
B15: BevCo | C15: 1185732 | D15: 44584 | E15: Northeast | F15: New York | G15: New York | H15: Powerade | I15: 0.6 | J15: 9000 | K15: 5400 | L15: 1620 | M15: 0.3
B16: BevCo | C16: 1185732 | D16: 44585 | E16: Northeast | F16: New York | G16: New York | H16: Dasani Water | I16: 0.5 | J16: 10000 | K16: 5000 | L16: 1250 | M16: 0.25
... B9652: BevCo | C9652: 1185732 | D9652: 44979 | E9652: Northeast | F9652: New Hampshire | G9652: Manchester | H9652: Sprite | I9652: 0.29 | J9652: 830 | K9652: 240.7 | L9652: 64.989 | M9652: 0.27

Sheet Dashboard
C10: Sales by Beverage Brand | J10: Sales by Retailer
C11: Brand | D11: Sales 2022 | E11: Sales 2023 | F11: Varience | J11: Brand | K11: Sales 2022 | L11: Sales 2023 | M11: Varience
C12: =Sheet1!A9 -> Coca-Cola | D12: =Sheet1!B9 -> 499102 | E12: =Sheet1!C9 -> 2268974.9 | F12: =E12-D12 -> 1769872.9 | J12: =Sheet1!A20 -> Amazon | K12: =Sheet1!B20 -> 276210 | L12: =Sheet1!C20 -> 1009698.7 | M12: =Sheet1!D20 -> 1285908.7
C13: =Sheet1!A10 -> Dasani Water | D13: =Sheet1!B10 -> 469270.7 | E13: =Sheet1!C10 -> 1917827.8 | F13: =E13-D13 -> 1448557.1 | J13: =Sheet1!A21 -> BevCo | K13: =Sheet1!B21 -> 466788 | L13: =Sheet1!C21 -> 2327606.5 | M13: =Sheet1!D21 -> 2794394.5
C14: =Sheet1!A11 -> Diet Coke | D14: =Sheet1!B11 -> 423758.7 | E14: =Sheet1!C11 -> 1633959.3 | F14: =E14-D14 -> 1210200.6 | J14: =Sheet1!A22 -> FizzyCo | K14: =Sheet1!B22 -> 161210.1 | L14: =Sheet1!C22 -> 2262827.1 | M14: =Sheet1!D22 -> 2424037.2
C15: =Sheet1!A12 -> Fanta | D15: =Sheet1!B12 -> 315489.2 | E15: =Sheet1!C12 -> 1116062.9 | F15: =E15-D15 -> 800573.7 | J15: =Sheet1!A23 -> Target | K15: =Sheet1!B23 -> 9250.3 | L15: =Sheet1!C23 -> 1341995 | M15: =Sheet1!D23 -> 1351245.3
C16: =Sheet1!A13 -> Powerade | D16: =Sheet1!B13 -> 349533.9 | E16: =Sheet1!C13 -> 1302529.3 | F16: =E16-D16 -> 952995.4 | J16: =Sheet1!A24 -> Walmart | K16: =Sheet1!B24 -> 339912.5 | L16: =Sheet1!C24 -> 580211 | M16: =Sheet1!D24 -> 920123.5
C17: =Sheet1!A14 -> Sprite | D17: =Sheet1!B14 -> 366578 | E17: =Sheet1!C14 -> 1353578.3 | F17: =E17-D17 -> 987000.3 | J17: =Sheet1!A25 -> West Soda | K17: =Sheet1!B25 -> 1170361.6 | L17: =Sheet1!C25 -> 2070594.2 | M17: =Sheet1!D25 -> 3240955.8
C18: Total | D18: =Sheet1!B15 -> 2423732.5 | E18: =Sheet1!C15 -> 9592932.5 | F18: =E18-D18 -> 7169200 | J18: Total | K18: =Sheet1!B26 -> 2423732.5 | L18: =Sheet1!C26 -> 9592932.5 | M18: =Sheet1!D26 -> 12016665
C21: Sales and Operating profit by quarter

Sheet Sheet2
C16: Total Sales By Beverage Brand | L16: Total Sales By Retailer
C17: Product | D17: Sales2022 | E17: Sales2023 | F17: Variance | L17: Brand | M17: Sales2022 | N17: Sales 2023 | O17: Variance
C18: =Sheet3!A9 -> Coca-Cola | D18: =Sheet3!B9 -> 84857 | E18: =Sheet3!C9 -> 384526.6 | F18: =E18-D18 -> 299669.6 | L18: =Sheet3!A20 -> Amazon | M18: =Sheet3!B20 -> 0 | N18: =Sheet3!C20 -> 133200.8 | O18: =N18-M18 -> 133200.8
C19: =Sheet3!A10 -> Dasani Water | D19: =Sheet3!B10 -> 76834 | E19: =Sheet3!C10 -> 334144.6 | F19: =E19-D19 -> 257310.6 | L19: =Sheet3!A21 -> BevCo | M19: =Sheet3!B21 -> 117386.1 | N19: =Sheet3!C21 -> 659450.7 | O19: =N19-M19 -> 542064.6
C20: =Sheet3!A11 -> Diet Coke | D20: =Sheet3!B11 -> 59939 | E20: =Sheet3!C11 -> 305425.5 | F20: =E20-D20 -> 245486.5 | L20: =Sheet3!A22 -> FizzyCo | M20: =Sheet3!B22 -> 114876 | N20: =Sheet3!C22 -> 589183.3 | O20: =N20-M20 -> 474307.3
C21: =Sheet3!A12 -> Fanta | D21: =Sheet3!B12 -> 48147.7 | E21: =Sheet3!C12 -> 219257.1 | F21: =E21-D21 -> 171109.4 | L21: =Sheet3!A23 -> Walmart | M21: =Sheet3!B23 -> 0 | N21: =Sheet3!C23 -> 299203.9 | O21: =N21-M21 -> 299203.9
C22: =Sheet3!A13 -> Powerade | D22: =Sheet3!B13 -> 66209.2 | E22: =Sheet3!C13 -> 252114.5 | F22: =E22-D22 -> 185905.3 | L22: =Sheet3!A24 -> West Soda | M22: =Sheet3!B24 -> 155149.2 | N22: =Sheet3!C24 -> 68993.6 | O22: =N22-M22 -> -86155.6
C23: =Sheet3!A14 -> Sprite | D23: =Sheet3!B14 -> 51424.4 | E23: =Sheet3!C14 -> 254564 | F23: =E23-D23 -> 203139.6 | L23: =Sheet3!A25 -> Total | M23: =Sheet3!B25 -> 387411.3 | N23: =Sheet3!C25 -> 1750032.3 | O23: =N23-M23 -> 1362621
C24: =Sheet3!A15 -> Total | D24: =Sheet3!B15 -> 387411.3 | E24: =Sheet3!C15 -> 1750032.3 | F24: =E24-D24 -> 1362621 | L24: =Sheet3!A26 -> 0 | M24: =Sheet3!B26 -> 0 | N24: =Sheet3!C26 -> 0 | O24: =N24-M24 -> 0
D29: Sales By Operating Profit By Quarter

Sheet Sheet6
D17: Total Sales By Beverage Brand | L17: Total Sales By Retailer
D18: Product | E18: Sales2022 | F18: Sales2023 | G18: Variance | L18: Brand | M18: Sales2022 | N18: Sales2023 | O18: Variance
D19: =Sheet3!A9 -> Coca-Cola | E19: =Sheet3!B9 -> 84857 | F19: =Sheet3!C9 -> 384526.6 | G19: =F19-E19 -> 299669.6 | L19: =Sheet3!A20 -> Amazon | M19: =Sheet3!B20 -> 0 | N19: =Sheet3!C20 -> 133200.8 | O19: =N19-M19 -> 133200.8
D20: =Sheet3!A10 -> Dasani Water | E20: =Sheet3!B10 -> 76834 | F20: =Sheet3!C10 -> 334144.6 | G20: =F20-E20 -> 257310.6 | L20: =Sheet3!A21 -> BevCo | M20: =Sheet3!B21 -> 117386.1 | N20: =Sheet3!C21 -> 659450.7 | O20: =N20-M20 -> 542064.6
D21: =Sheet3!A11 -> Diet Coke | E21: =Sheet3!B11 -> 59939 | F21: =Sheet3!C11 -> 305425.5 | G21: =F21-E21 -> 245486.5 | L21: =Sheet3!A22 -> FizzyCo | M21: =Sheet3!B22 -> 114876 | N21: =Sheet3!C22 -> 589183.3 | O21: =N21-M21 -> 474307.3
D22: =Sheet3!A12 -> Fanta | E22: =Sheet3!B12 -> 48147.7 | F22: =Sheet3!C12 -> 219257.1 | G22: =F22-E22 -> 171109.4 | L22: =Sheet3!A23 -> Walmart | M22: =Sheet3!B23 -> 0 | N22: =Sheet3!C23 -> 299203.9 | O22: =N22-M22 -> 299203.9
D23: =Sheet3!A13 -> Powerade | E23: =Sheet3!B13 -> 66209.2 | F23: =Sheet3!C13 -> 252114.5 | G23: =F23-E23 -> 185905.3 | L23: =Sheet3!A24 -> West Soda | M23: =Sheet3!B24 -> 155149.2 | N23: =Sheet3!C24 -> 68993.6 | O23: =N23-M23 -> -86155.6
D24: =Sheet3!A14 -> Sprite | E24: =Sheet3!B14 -> 51424.4 | F24: =Sheet3!C14 -> 254564 | G24: =F24-E24 -> 203139.6 | L24: =Sheet3!A25 -> Total | M24: =Sheet3!B25 -> 387411.3 | N24: =Sheet3!C25 -> 1750032.3 | O24: =N24-M24 -> 1362621
D25: =Sheet3!A15 -> Total | E25: =Sheet3!B15 -> 387411.3 | F25: =Sheet3!C15 -> 1750032.3 | G25: =F25-E25 -> 1362621
F29: Sales By Operating Profit By Quarter
